enhancedinput/__init__.py
enhancedinput/colors.py
enhancedinput/enhancedinput.py
enhancedinput/themes.py
enhancedinput/validator.py
EnhancedInput-0.1.1.dist-info/LICENSE.txt
EnhancedInput-0.1.1.dist-info/METADATA
EnhancedInput-0.1.1.dist-info/WHEEL
EnhancedInput-0.1.1.dist-info/top_level.txt
EnhancedInput-0.1.1.dist-info/RECORD
