Metadata-Version: 2.1
Name: EnhancedInput
Version: 0.1.1
Summary: A package to enhance the input function in Python
Home-page: https://github.com/alec-jensen/EnhancedInput
Author: Alec Jensen
Author-email: Alec Jensen <alec@alecj.tk>
License: MIT
Keywords: input,enhanced,python
Platform: any
Requires-Python: >=3.11
License-File: LICENSE.txt
Requires-Dist: urllib3 >=2.2.1
Provides-Extra: testing
Requires-Dist: setuptools ; extra == 'testing'
Requires-Dist: pytest ; extra == 'testing'
Requires-Dist: pytest-cov ; extra == 'testing'
